hitch_pip_tools-1.8.3.dist-info/DESCRIPTION.rst
hitch_pip_tools-1.8.3.dist-info/METADATA
hitch_pip_tools-1.8.3.dist-info/RECORD
hitch_pip_tools-1.8.3.dist-info/WHEEL
hitch_pip_tools-1.8.3.dist-info/entry_points.txt
hitch_pip_tools-1.8.3.dist-info/metadata.json
hitch_pip_tools-1.8.3.dist-info/top_level.txt
piptools/__init__.py
piptools/cache.py
piptools/click.py
piptools/exceptions.py
piptools/io.py
piptools/locations.py
piptools/logging.py
piptools/resolver.py
piptools/sync.py
piptools/utils.py
piptools/writer.py
piptools/_compat/__init__.py
piptools/_compat/contextlib.py
piptools/_compat/tempfile.py
piptools/repositories/__init__.py
piptools/repositories/base.py
piptools/repositories/local.py
piptools/repositories/pypi.py
piptools/scripts/__init__.py
piptools/scripts/compile.py
piptools/scripts/sync.py
