Metadata-Version: 2.0
Name: hitch-pip-tools
Version: 1.8.3
Summary: 
Requires-Dist: click (>=6)
Requires-Dist: first
Requires-Dist: six
